[
 {
  "trends": [
   {
    "name": "#WTC2021Final",
    "url": "http://twitter.com/search?q=%23WTC2021Final",
    "promoted_content": null,
    "query": "%23WTC2021Final",
    "tweet_volume": null
   },
   {
    "name": "#\u0939\u092e\u093e\u0930\u0947_\u092a\u094d\u092f\u093e\u0930\u0947_\u092e\u094b\u0926\u0940_\u091c\u0940",
    "url": "http://twitter.com/search?q=%23%E0%A4%B9%E0%A4%AE%E0%A4%BE%E0%A4%B0%E0%A5%87_%E0%A4%AA%E0%A5%8D%E0%A4%AF%E0%A4%BE%E0%A4%B0%E0%A5%87_%E0%A4%AE%E0%A5%8B%E0%A4%A6%E0%A5%80_%E0%A4%9C%E0%A5%80",
    "promoted_content": null,
    "query": "%23%E0%A4%B9%E0%A4%AE%E0%A4%BE%E0%A4%B0%E0%A5%87_%E0%A4%AA%E0%A5%8D%E0%A4%AF%E0%A4%BE%E0%A4%B0%E0%A5%87_%E0%A4%AE%E0%A5%8B%E0%A4%A6%E0%A5%80_%E0%A4%9C%E0%A5%80",
    "tweet_volume": 12297
   },
   {
    "name": "Pant",
    "url": "http://twitter.com/search?q=Pant",
    "promoted_content": null,
    "query": "Pant",
    "tweet_volume": 21450
   },
   {
    "name": "#SharkTankComesToIndia",
    "url": "http://twitter.com/search?q=%23SharkTankComesToIndia",
    "promoted_content": null,
    "query": "%23SharkTankComesToIndia",
    "tweet_volume": null
   },
   {
    "name": "#NaaneVaruven",
    "url": "http://twitter.com/search?q=%23NaaneVaruven",
    "promoted_content": null,
    "query": "%23NaaneVaruven",
    "tweet_volume": 14148
   },
   {
    "name": "Rahane",
    "url": "http://twitter.com/search?q=Rahane",
    "promoted_content": null,
    "query": "Rahane",
    "tweet_volume": null
   },
   {
    "name": "Be A ConservationHero",
    "url": "http://twitter.com/search?q=%22Be+A+ConservationHero%22",
    "promoted_content": null,
    "query": "%22Be+A+ConservationHero%22",
    "tweet_volume": null
   },
   {
    "name": "JASMINs BDAY WEEK",
    "url": "http://twitter.com/search?q=%22JASMINs+BDAY+WEEK%22",
    "promoted_content": null,
    "query": "%22JASMINs+BDAY+WEEK%22",
    "tweet_volume": 11448
   },
   {
    "name": "Disha Sushant Murder Proofs",
    "url": "http://twitter.com/search?q=%22Disha+Sushant+Murder+Proofs%22",
    "promoted_content": null,
    "query": "%22Disha+Sushant+Murder+Proofs%22",
    "tweet_volume": 133151
   },
   {
    "name": "Kohli",
    "url": "http://twitter.com/search?q=Kohli",
    "promoted_content": null,
    "query": "Kohli",
    "tweet_volume": 43611
   },
   {
    "name": "Shirmal",
    "url": "http://twitter.com/search?q=Shirmal",
    "promoted_content": null,
    "query": "Shirmal",
    "tweet_volume": null
   },
   {
    "name": "cppune mission clear crime",
    "url": "http://twitter.com/search?q=%22cppune+mission+clear+crime%22",
    "promoted_content": null,
    "query": "%22cppune+mission+clear+crime%22",
    "tweet_volume": null
   },
   {
    "name": "1M ABHINAV INSTA ARMY",
    "url": "http://twitter.com/search?q=%221M+ABHINAV+INSTA+ARMY%22",
    "promoted_content": null,
    "query": "%221M+ABHINAV+INSTA+ARMY%22",
    "tweet_volume": 30035
   },
   {
    "name": "Wagner",
    "url": "http://twitter.com/search?q=Wagner",
    "promoted_content": null,
    "query": "Wagner",
    "tweet_volume": 13787
   },
   {
    "name": "Jamieson",
    "url": "http://twitter.com/search?q=Jamieson",
    "promoted_content": null,
    "query": "Jamieson",
    "tweet_volume": 12913
   },
   {
    "name": "SafeRaho UPIkaro",
    "url": "http://twitter.com/search?q=%22SafeRaho+UPIkaro%22",
    "promoted_content": null,
    "query": "%22SafeRaho+UPIkaro%22",
    "tweet_volume": null
   },
   {
    "name": "Iqbal Kaskar",
    "url": "http://twitter.com/search?q=%22Iqbal+Kaskar%22",
    "promoted_content": null,
    "query": "%22Iqbal+Kaskar%22",
    "tweet_volume": null
   },
   {
    "name": "Vijay Mallya",
    "url": "http://twitter.com/search?q=%22Vijay+Mallya%22",
    "promoted_content": null,
    "query": "%22Vijay+Mallya%22",
    "tweet_volume": 13682
   },
   {
    "name": "1M IG POSTS ADMIRING DISHUL",
    "url": "http://twitter.com/search?q=%221M+IG+POSTS+ADMIRING+DISHUL%22",
    "promoted_content": null,
    "query": "%221M+IG+POSTS+ADMIRING+DISHUL%22",
    "tweet_volume": 47760
   },
   {
    "name": "\u0939\u093e\u092b\u093f\u091c \u0938\u0908\u0926",
    "url": "http://twitter.com/search?q=%22%E0%A4%B9%E0%A4%BE%E0%A4%AB%E0%A4%BF%E0%A4%9C+%E0%A4%B8%E0%A4%88%E0%A4%A6%22",
    "promoted_content": null,
    "query": "%22%E0%A4%B9%E0%A4%BE%E0%A4%AB%E0%A4%BF%E0%A4%9C+%E0%A4%B8%E0%A4%88%E0%A4%A6%22",
    "tweet_volume": null
   },
   {
    "name": "Gabba",
    "url": "http://twitter.com/search?q=Gabba",
    "promoted_content": null,
    "query": "Gabba",
    "tweet_volume": null
   },
   {
    "name": "Jaddu",
    "url": "http://twitter.com/search?q=Jaddu",
    "promoted_content": null,
    "query": "Jaddu",
    "tweet_volume": null
   },
   {
    "name": "BAARISH BAN JAANA HITS 100M",
    "url": "http://twitter.com/search?q=%22BAARISH+BAN+JAANA+HITS+100M%22",
    "promoted_content": null,
    "query": "%22BAARISH+BAN+JAANA+HITS+100M%22",
    "tweet_volume": 10105
   },
   {
    "name": "Mehul Choksi",
    "url": "http://twitter.com/search?q=%22Mehul+Choksi%22",
    "promoted_content": null,
    "query": "%22Mehul+Choksi%22",
    "tweet_volume": 12747
   },
   {
    "name": "Draw",
    "url": "http://twitter.com/search?q=Draw",
    "promoted_content": null,
    "query": "Draw",
    "tweet_volume": 215228
   },
   {
    "name": "Sylvie",
    "url": "http://twitter.com/search?q=Sylvie",
    "promoted_content": null,
    "query": "Sylvie",
    "tweet_volume": 31810
   },
   {
    "name": "BJ Watling",
    "url": "http://twitter.com/search?q=%22BJ+Watling%22",
    "promoted_content": null,
    "query": "%22BJ+Watling%22",
    "tweet_volume": null
   },
   {
    "name": "Southee",
    "url": "http://twitter.com/search?q=Southee",
    "promoted_content": null,
    "query": "Southee",
    "tweet_volume": 10348
   },
   {
    "name": "\u0936\u094d\u092f\u093e\u092e\u093e \u092a\u094d\u0930\u0938\u093e\u0926 \u092e\u0941\u0916\u0930\u094d\u091c\u0940",
    "url": "http://twitter.com/search?q=%22%E0%A4%B6%E0%A5%8D%E0%A4%AF%E0%A4%BE%E0%A4%AE%E0%A4%BE+%E0%A4%AA%E0%A5%8D%E0%A4%B0%E0%A4%B8%E0%A4%BE%E0%A4%A6+%E0%A4%AE%E0%A5%81%E0%A4%96%E0%A4%B0%E0%A5%8D%E0%A4%9C%E0%A5%80%22",
    "promoted_content": null,
    "query": "%22%E0%A4%B6%E0%A5%8D%E0%A4%AF%E0%A4%BE%E0%A4%AE%E0%A4%BE+%E0%A4%AA%E0%A5%8D%E0%A4%B0%E0%A4%B8%E0%A4%BE%E0%A4%A6+%E0%A4%AE%E0%A5%81%E0%A4%96%E0%A4%B0%E0%A5%8D%E0%A4%9C%E0%A5%80%22",
    "tweet_volume": 70240
   },
   {
    "name": "BLACKPINK",
    "url": "http://twitter.com/search?q=BLACKPINK",
    "promoted_content": null,
    "query": "BLACKPINK",
    "tweet_volume": 1167003
   },
   {
    "name": "#LahoreBlast",
    "url": "http://twitter.com/search?q=%23LahoreBlast",
    "promoted_content": null,
    "query": "%23LahoreBlast",
    "tweet_volume": null
   },
   {
    "name": "#\u091d\u0917\u0921\u093c\u093e\u0932\u0942_\u092e\u094b\u0926\u0940",
    "url": "http://twitter.com/search?q=%23%E0%A4%9D%E0%A4%97%E0%A4%A1%E0%A4%BC%E0%A4%BE%E0%A4%B2%E0%A5%82_%E0%A4%AE%E0%A5%8B%E0%A4%A6%E0%A5%80",
    "promoted_content": null,
    "query": "%23%E0%A4%9D%E0%A4%97%E0%A4%A1%E0%A4%BC%E0%A4%BE%E0%A4%B2%E0%A5%82_%E0%A4%AE%E0%A5%8B%E0%A4%A6%E0%A5%80",
    "tweet_volume": 18387
   },
   {
    "name": "#BlinksApologizeToBTS",
    "url": "http://twitter.com/search?q=%23BlinksApologizeToBTS",
    "promoted_content": null,
    "query": "%23BlinksApologizeToBTS",
    "tweet_volume": 14334
   },
   {
    "name": "#WTC21",
    "url": "http://twitter.com/search?q=%23WTC21",
    "promoted_content": null,
    "query": "%23WTC21",
    "tweet_volume": 35705
   },
   {
    "name": "#Loki",
    "url": "http://twitter.com/search?q=%23Loki",
    "promoted_content": null,
    "query": "%23Loki",
    "tweet_volume": 159135
   },
   {
    "name": "#Butter11thWin",
    "url": "http://twitter.com/search?q=%23Butter11thWin",
    "promoted_content": null,
    "query": "%23Butter11thWin",
    "tweet_volume": 137086
   },
   {
    "name": "#WeLoveYouShehnaaz",
    "url": "http://twitter.com/search?q=%23WeLoveYouShehnaaz",
    "promoted_content": null,
    "query": "%23WeLoveYouShehnaaz",
    "tweet_volume": 101274
   },
   {
    "name": "#HafizSaeed",
    "url": "http://twitter.com/search?q=%23HafizSaeed",
    "promoted_content": null,
    "query": "%23HafizSaeed",
    "tweet_volume": null
   },
   {
    "name": "#INDvsNZ",
    "url": "http://twitter.com/search?q=%23INDvsNZ",
    "promoted_content": null,
    "query": "%23INDvsNZ",
    "tweet_volume": 19416
   },
   {
    "name": "#JusticeforMurugesan",
    "url": "http://twitter.com/search?q=%23JusticeforMurugesan",
    "promoted_content": null,
    "query": "%23JusticeforMurugesan",
    "tweet_volume": 15610
   },
   {
    "name": "#\u0915\u093f\u0938\u093e\u0928\u094b\u0902_\u0915\u093e_\u092e\u0938\u0940\u0939\u093e_\u0906\u092f\u093e",
    "url": "http://twitter.com/search?q=%23%E0%A4%95%E0%A4%BF%E0%A4%B8%E0%A4%BE%E0%A4%A8%E0%A5%8B%E0%A4%82_%E0%A4%95%E0%A4%BE_%E0%A4%AE%E0%A4%B8%E0%A5%80%E0%A4%B9%E0%A4%BE_%E0%A4%86%E0%A4%AF%E0%A4%BE",
    "promoted_content": null,
    "query": "%23%E0%A4%95%E0%A4%BF%E0%A4%B8%E0%A4%BE%E0%A4%A8%E0%A5%8B%E0%A4%82_%E0%A4%95%E0%A4%BE_%E0%A4%AE%E0%A4%B8%E0%A5%80%E0%A4%B9%E0%A4%BE_%E0%A4%86%E0%A4%AF%E0%A4%BE",
    "tweet_volume": null
   },
   {
    "name": "#ICCWorldTestChampionship",
    "url": "http://twitter.com/search?q=%23ICCWorldTestChampionship",
    "promoted_content": null,
    "query": "%23ICCWorldTestChampionship",
    "tweet_volume": null
   },
   {
    "name": "#btsdiamond",
    "url": "http://twitter.com/search?q=%23btsdiamond",
    "promoted_content": null,
    "query": "%23btsdiamond",
    "tweet_volume": 350885
   },
   {
    "name": "#Selvaraghavan",
    "url": "http://twitter.com/search?q=%23Selvaraghavan",
    "promoted_content": null,
    "query": "%23Selvaraghavan",
    "tweet_volume": null
   },
   {
    "name": "#NiravModi",
    "url": "http://twitter.com/search?q=%23NiravModi",
    "promoted_content": null,
    "query": "%23NiravModi",
    "tweet_volume": null
   },
   {
    "name": "#Shopian",
    "url": "http://twitter.com/search?q=%23Shopian",
    "promoted_content": null,
    "query": "%23Shopian",
    "tweet_volume": null
   },
   {
    "name": "#dawoodibrahim",
    "url": "http://twitter.com/search?q=%23dawoodibrahim",
    "promoted_content": null,
    "query": "%23dawoodibrahim",
    "tweet_volume": null
   },
   {
    "name": "#KGF2",
    "url": "http://twitter.com/search?q=%23KGF2",
    "promoted_content": null,
    "query": "%23KGF2",
    "tweet_volume": null
   },
   {
    "name": "#NZvIND",
    "url": "http://twitter.com/search?q=%23NZvIND",
    "promoted_content": null,
    "query": "%23NZvIND",
    "tweet_volume": null
   }
  ],
  "as_of": "2021-06-23T12:45:43Z",
  "created_at": "2021-06-22T21:13:10Z",
  "locations": [
   {
    "name": "Nagpur",
    "woeid": 2282863
   }
  ]
 }
]